iLiaShahpy/Clien.py
iLiaShahpy/Copyright.py
iLiaShahpy/Device.py
iLiaShahpy/Encoder.py
iLiaShahpy/Error.py
iLiaShahpy/Getheader.py
iLiaShahpy/GtM.py
iLiaShahpy/PostData.py
iLiaShahpy/TrubText.py
iLiaShahpy/ZedLink.py
iLiaShahpy/__init__.py
iLiaShahpy/iLia.py
iLiaShahpy-3.8.6.dist-info/LICENCE
iLiaShahpy-3.8.6.dist-info/METADATA
iLiaShahpy-3.8.6.dist-info/WHEEL
iLiaShahpy-3.8.6.dist-info/top_level.txt
iLiaShahpy-3.8.6.dist-info/RECORD
